mridu_manda/__init__.py
mridu_manda/main.py
mridu_manda/setup_mridumanda.py
mridu_manda/setup_weather_data.py
mridu_manda-0.9.0.dist-info/LICENSE
mridu_manda-0.9.0.dist-info/METADATA
mridu_manda-0.9.0.dist-info/WHEEL
mridu_manda-0.9.0.dist-info/entry_points.txt
mridu_manda-0.9.0.dist-info/RECORD
