Metadata-Version: 2.3
Name: mridu-manda
Version: 0.9.0
Summary: 
Author: Shvetank Dattatreya
Author-email: hello.shvetank@gmail.com
Requires-Python: >=3.10
Classifier: Programming Language :: Python :: 3
Classifier: Programming Language :: Python :: 3.10
Classifier: Programming Language :: Python :: 3.11
Classifier: Programming Language :: Python :: 3.12
Classifier: Programming Language :: Python :: 3.13
Requires-Dist: requests (>=2.32.4,<3.0.0)
